pollination_dsl/__init__.py
pollination_dsl/cli.py
pollination_dsl/common.py
pollination_dsl/package.py
pollination_dsl/alias/__init__.py
pollination_dsl/alias/inputs.py
pollination_dsl/alias/outputs.py
pollination_dsl/dag/__init__.py
pollination_dsl/dag/base.py
pollination_dsl/dag/inputs.py
pollination_dsl/dag/outputs.py
pollination_dsl/dag/task.py
pollination_dsl/function/__init__.py
pollination_dsl/function/base.py
pollination_dsl/function/inputs.py
pollination_dsl/function/outputs.py
pollination_dsl-0.17.1.dist-info/LICENSE
pollination_dsl-0.17.1.dist-info/METADATA
pollination_dsl-0.17.1.dist-info/WHEEL
pollination_dsl-0.17.1.dist-info/entry_points.txt
pollination_dsl-0.17.1.dist-info/top_level.txt
pollination_dsl-0.17.1.dist-info/RECORD
