Metadata-Version: 2.1
Name: pollination-dsl
Version: 0.17.1
Summary: A Python DSL to create Pollination recipes and plugins.
Home-page: https://github.com/pollination/pollination-dsl
Author: Pollination
Author-email: info@pollination.solutions
Classifier: Programming Language :: Python :: 3.7
Classifier: Programming Language :: Python :: 3.10
Classifier: Programming Language :: Python :: Implementation :: CPython
Classifier: Operating System :: OS Independent
Requires-Python: >=3.7
License-File: LICENSE
Requires-Dist: queenbee-pollination==0.7.10
Requires-Dist: queenbee-local>=0.6.7
Requires-Dist: importlib-metadata>=6.6.0
